onpanda/__info__.py
onpanda/__init__.py
onpanda/parser.py
onpanda/test_utils.py
onpanda/token_level_supervision_utils.py
onpanda/utils.py
onpanda/arena/__init__.py
onpanda/arena/panda_battle.py
onpanda/correcting_model/__init__.py
onpanda/correcting_model/correcting_sft_model.py
onpanda/correcting_model/correcting_sft_utils.py
onpanda/correcting_model/is_good_score_mixin.py
onpanda/server/__init__.py
onpanda/server/main.py
onpanda-0.0.10.dist-info/METADATA
onpanda-0.0.10.dist-info/WHEEL
onpanda-0.0.10.dist-info/top_level.txt
onpanda-0.0.10.dist-info/RECORD
