Metadata-Version: 2.4
Name: onpanda
Version: 0.0.10
Summary: onPanda Python package
Home-page: https://github.com/on-panda/onpanda
Author: DIYer22
Author-email: ylxx@live.com
Classifier: Topic :: Software Development :: Libraries :: Python Modules
Classifier: Programming Language :: Python :: 3
Classifier: License :: OSI Approved :: MIT License
Classifier: Operating System :: OS Independent
Requires-Dist: mxlm>=0.2.1
Requires-Dist: fastapi
Requires-Dist: mximport
Dynamic: author
Dynamic: author-email
Dynamic: classifier
Dynamic: description
Dynamic: description-content-type
Dynamic: home-page
Dynamic: requires-dist
Dynamic: summary
